CHANGES.rst
LICENSE
MANIFEST.in
README.rst
setup.py
pyvka/__init__.py
pyvka/auth.py
pyvka/config.py
pyvka/exceptions.py
pyvka/parser.py
pyvka.egg-info/PKG-INFO
pyvka.egg-info/SOURCES.txt
pyvka.egg-info/dependency_links.txt
pyvka.egg-info/requires.txt
pyvka.egg-info/top_level.txt