Metadata-Version: 1.1
Name: pyvka
Version: 0.1
Summary: Python package for authorize and getaccess_token for vkontakte api.
Home-page: https://github.com/saippuakauppias/pyvka
Author: Denis Veselov
Author-email: progr.mail@gmail.com
License: ISC
Keywords: vkontakte vk api access_token oauth oauth2
Platform: UNKNOWN
Classifier: Development Status :: 5 - Production/Stable
Classifier: Intended Audience :: Developers
Classifier: License :: OSI Approved :: ISC License (ISCL)
Classifier: Operating System :: OS Independent
Classifier: Programming Language :: Python
Classifier: Programming Language :: Python :: 2.6
Classifier: Programming Language :: Python :: 2.7
Classifier: Topic :: Internet :: WWW/HTTP
